{"expireTime":9007200887853714000,"key":"7485ce528a8f5d39b3f6b18dc0b84a83","val":{"name":"IMAGE_PROCESSING","inputPaths":["/home/premashish/Documents/Web Development/Pgnith.github.io/src/images/cutoff.png"],"outputDir":"/home/premashish/Documents/Web Development/Pgnith.github.io/public/static/8cf01ad8438fd3c40926cb987b643738","args":{"isLazy":false,"operations":[{"outputPath":"d67c1/cutoff.webp","args":{"height":80,"width":100,"cropFocus":17,"toFormat":"webp","fit":"cover"}},{"outputPath":"923ce/cutoff.webp","args":{"height":160,"width":200,"cropFocus":17,"toFormat":"webp","fit":"cover"}},{"outputPath":"33402/cutoff.webp","args":{"height":320,"width":400,"cropFocus":17,"toFormat":"webp","fit":"cover"}},{"outputPath":"41401/cutoff.webp","args":{"height":640,"width":800,"cropFocus":17,"toFormat":"webp","fit":"cover"}}],"pluginOptions":{"base64Width":20,"forceBase64Format":"","useMozJpeg":false,"stripMetadata":true,"lazyImageGeneration":true,"defaultQuality":50,"failOnError":true,"plugins":[]}}}}